isolate_controller/__init__.py
isolate_controller/auth.py
isolate_controller/definitions/__init__.py
isolate_controller/definitions/controller.proto
isolate_controller/definitions/controller_pb2.py
isolate_controller/definitions/controller_pb2.pyi
isolate_controller/definitions/controller_pb2_grpc.py
isolate_controller/flags.py
isolate_controller/google_storage.py
isolate_controller/layers.py
isolate_controller/pg_db.py
isolate_controller/resources.py
isolate_controller/scheduler/__init__.py
isolate_controller/scheduler/_base.py
isolate_controller/scheduler/kubernetes.py
isolate_controller/scheduler/local.py
isolate_controller/server.py
isolate_controller/shared_db.py
isolate_controller-0.0.1a0.dist-info/WHEEL
isolate_controller-0.0.1a0.dist-info/METADATA
isolate_controller-0.0.1a0.dist-info/RECORD
