Metadata-Version: 2.1
Name: isolate-controller
Version: 0.0.1a0
Summary: Managed isolated environments for Python
Author: Features & Labels
Author-email: hello@fal.ai
Requires-Python: >=3.7,<4
Classifier: Programming Language :: Python :: 3
Classifier: Programming Language :: Python :: 3.7
Classifier: Programming Language :: Python :: 3.8
Classifier: Programming Language :: Python :: 3.9
Classifier: Programming Language :: Python :: 3.10
Classifier: Programming Language :: Python :: 3.11
Requires-Dist: dill (==0.3.5.1)
Requires-Dist: google-cloud-storage (>=2.6.0,<3.0.0)
Requires-Dist: grpcio (>=1.49)
Requires-Dist: isolate (==0.5.0)
Requires-Dist: kubernetes (>=25.3.0,<26.0.0)
Requires-Dist: kubernetes-asyncio (>=24.2.2,<25.0.0)
Requires-Dist: protobuf
Requires-Dist: psycopg (>=3.1.4,<4.0.0)
Requires-Dist: redis (>=4.3.4,<5.0.0)
Requires-Dist: typing-extensions (>=4.4.0,<5.0.0)
